{"metadata": {"dbt_schema_version": "https://schemas.getdbt.com/dbt/run-results/v6.json", "dbt_version": "1.10.3", "generated_at": "2025-08-27T18:25:31.852882Z", "invocation_id": "47e56484-127b-4297-a1e0-265902947f16", "invocation_started_at": "2025-08-27T18:25:06.380152Z", "env": {}}, "results": [{"status": "success", "timing": [{"name": "compile", "started_at": "2025-08-27T18:25:14.820340Z", "completed_at": "2025-08-27T18:25:14.847373Z"}, {"name": "execute", "started_at": "2025-08-27T18:25:14.850462Z", "completed_at": "2025-08-27T18:25:16.214186Z"}], "thread_id": "Thread-1 (worker)", "execution_time": 1.3938465118408203, "adapter_response": {"_message": "OK", "query_id": "01f08373-2d8d-1aaa-a34b-e35f26dab778"}, "message": "OK", "failures": null, "unique_id": "model.dbt_databricks_cicd.src_ecommerce", "compiled": true, "compiled_code": "\n\nSELECT * FROM default.sales_ecommerce", "relation_name": "`workspace`.`default`.`src_ecommerce`", "batch_results": null}, {"status": "success", "timing": [{"name": "compile", "started_at": "2025-08-27T18:25:16.229815Z", "completed_at": "2025-08-27T18:25:16.252908Z"}, {"name": "execute", "started_at": "2025-08-27T18:25:16.254907Z", "completed_at": "2025-08-27T18:25:16.826722Z"}], "thread_id": "Thread-1 (worker)", "execution_time": 0.596907377243042, "adapter_response": {"_message": "OK", "query_id": "01f08373-2df0-1f83-8d97-f669b8d6746d"}, "message": "OK", "failures": null, "unique_id": "model.dbt_databricks_cicd.stg_ecommerce", "compiled": true, "compiled_code": "\n\nSELECT\n  User_ID,\n  Product_ID,\n  Category,\n  Price,\n  Discount,\n  Final_Price,\n  Payment_Method,\n  Purchase_Date\nFROM `workspace`.`default`.`src_ecommerce`", "relation_name": "`workspace`.`default`.`stg_ecommerce`", "batch_results": null}, {"status": "success", "timing": [{"name": "compile", "started_at": "2025-08-27T18:25:16.854702Z", "completed_at": "2025-08-27T18:25:16.867520Z"}, {"name": "execute", "started_at": "2025-08-27T18:25:16.869517Z", "completed_at": "2025-08-27T18:25:17.448893Z"}], "thread_id": "Thread-1 (worker)", "execution_time": 0.605189323425293, "adapter_response": {"_message": "OK", "query_id": "01f08373-2e50-127b-98b4-acf9d123ffef"}, "message": "OK", "failures": null, "unique_id": "model.dbt_databricks_cicd.avg_discount_by_category", "compiled": true, "compiled_code": "\n\nSELECT\n  Category,\n  ROUND(AVG(CAST(`Discount` AS DOUBLE)), 2) AS avg_discount_percent\nFROM `workspace`.`default`.`stg_ecommerce`\nGROUP BY Category\nORDER BY avg_discount_percent DESC", "relation_name": "`workspace`.`default`.`avg_discount_by_category`", "batch_results": null}, {"status": "success", "timing": [{"name": "compile", "started_at": "2025-08-27T18:25:17.461854Z", "completed_at": "2025-08-27T18:25:17.472859Z"}, {"name": "execute", "started_at": "2025-08-27T18:25:17.474856Z", "completed_at": "2025-08-27T18:25:18.127409Z"}], "thread_id": "Thread-1 (worker)", "execution_time": 0.6695554256439209, "adapter_response": {"_message": "OK", "query_id": "01f08373-2eac-15a0-af55-e5dc44738bfc"}, "message": "OK", "failures": null, "unique_id": "model.dbt_databricks_cicd.avg_ticket_by_category", "compiled": true, "compiled_code": "\n\nSELECT\n  Category,\n  ROUND(AVG(CAST(REPLACE(`Final_Price`, ',', '.') AS DOUBLE)), 2) AS avg_ticket\nFROM `workspace`.`default`.`stg_ecommerce`\nGROUP BY Category\nORDER BY avg_ticket DESC", "relation_name": "`workspace`.`default`.`avg_ticket_by_category`", "batch_results": null}, {"status": "success", "timing": [{"name": "compile", "started_at": "2025-08-27T18:25:18.134207Z", "completed_at": "2025-08-27T18:25:18.153144Z"}, {"name": "execute", "started_at": "2025-08-27T18:25:18.153144Z", "completed_at": "2025-08-27T18:25:18.805160Z"}], "thread_id": "Thread-1 (worker)", "execution_time": 0.6719522476196289, "adapter_response": {"_message": "OK", "query_id": "01f08373-2f15-1114-8533-34c486e6413d"}, "message": "OK", "failures": null, "unique_id": "model.dbt_databricks_cicd.monthly_revenue", "compiled": true, "compiled_code": "\n\nSELECT\n  CAST(DATE_TRUNC('month', CAST(Purchase_Date AS DATE)) AS DATE) AS month,\n  ROUND(SUM(CAST(REPLACE(`Final_Price`, ',', '.') AS DOUBLE)), 2) AS monthly_revenue\nFROM `workspace`.`default`.`stg_ecommerce`\nGROUP BY 1\nORDER BY 1", "relation_name": "`workspace`.`default`.`monthly_revenue`", "batch_results": null}, {"status": "success", "timing": [{"name": "compile", "started_at": "2025-08-27T18:25:18.821699Z", "completed_at": "2025-08-27T18:25:18.836991Z"}, {"name": "execute", "started_at": "2025-08-27T18:25:18.838990Z", "completed_at": "2025-08-27T18:25:19.479073Z"}], "thread_id": "Thread-1 (worker)", "execution_time": 0.6613783836364746, "adapter_response": {"_message": "OK", "query_id": "01f08373-2f7c-1a9b-ad42-b5bab960164b"}, "message": "OK", "failures": null, "unique_id": "model.dbt_databricks_cicd.payment_distribution", "compiled": true, "compiled_code": "\n\n\n\nSELECT\n  Payment_Method,\n  COUNT(*) AS total_transactions,\n  ROUND(SUM(CAST(REPLACE(`Final_Price`, ',', '.') AS DOUBLE)), 2) AS total_value\nFROM `workspace`.`default`.`stg_ecommerce`\nGROUP BY Payment_Method\nORDER BY total_value DESC", "relation_name": "`workspace`.`default`.`payment_distribution`", "batch_results": null}, {"status": "success", "timing": [{"name": "compile", "started_at": "2025-08-27T18:25:19.492604Z", "completed_at": "2025-08-27T18:25:19.505604Z"}, {"name": "execute", "started_at": "2025-08-27T18:25:19.507705Z", "completed_at": "2025-08-27T18:25:20.165084Z"}], "thread_id": "Thread-1 (worker)", "execution_time": 0.6767313480377197, "adapter_response": {"_message": "OK", "query_id": "01f08373-2fe1-1672-8fef-834bb6fee8cc"}, "message": "OK", "failures": null, "unique_id": "model.dbt_databricks_cicd.sales_by_category", "compiled": true, "compiled_code": "\n\nSELECT\n  Category,\n  COUNT(*) AS total_orders,\n  ROUND(SUM(CAST(REPLACE(`Final_Price`, ',', '.') AS DOUBLE)), 2) AS total_revenue\nFROM `workspace`.`default`.`stg_ecommerce`\nGROUP BY Category\nORDER BY total_revenue DESC", "relation_name": "`workspace`.`default`.`sales_by_category`", "batch_results": null}, {"status": "success", "timing": [{"name": "compile", "started_at": "2025-08-27T18:25:20.180720Z", "completed_at": "2025-08-27T18:25:20.180720Z"}, {"name": "execute", "started_at": "2025-08-27T18:25:20.180720Z", "completed_at": "2025-08-27T18:25:20.798108Z"}], "thread_id": "Thread-1 (worker)", "execution_time": 0.634026050567627, "adapter_response": {"_message": "OK", "query_id": "01f08373-3049-1878-bbad-85a04d00be8b"}, "message": "OK", "failures": null, "unique_id": "model.dbt_databricks_cicd.top_5_products", "compiled": true, "compiled_code": "\n\nWITH base AS (\n    SELECT\n        product_id,\n        ROUND(SUM(CAST(REPLACE(`Final_Price`, ',', '.') AS DOUBLE)), 2) AS total_sales\n    FROM `workspace`.`default`.`stg_ecommerce`\n    GROUP BY product_id\n)\n\nSELECT\n    product_id,\n    total_sales\nFROM base\nORDER BY total_sales DESC\nLIMIT 5", "relation_name": "`workspace`.`default`.`top_5_products`", "batch_results": null}, {"status": "success", "timing": [{"name": "compile", "started_at": "2025-08-27T18:25:20.813136Z", "completed_at": "2025-08-27T18:25:20.821108Z"}, {"name": "execute", "started_at": "2025-08-27T18:25:20.822074Z", "completed_at": "2025-08-27T18:25:21.488703Z"}], "thread_id": "Thread-1 (worker)", "execution_time": 0.6806347370147705, "adapter_response": {"_message": "OK", "query_id": "01f08373-30aa-1e1d-b3ef-c61194350341"}, "message": "OK", "failures": null, "unique_id": "model.dbt_databricks_cicd.top_customers", "compiled": true, "compiled_code": "\n\nSELECT\n  User_ID,\n  COUNT(*) AS total_orders,\n  ROUND(SUM(CAST(REPLACE(`Final_Price`, ',', '.') AS DOUBLE)), 2) AS total_spent\nFROM `workspace`.`default`.`stg_ecommerce`\nGROUP BY User_ID\nORDER BY total_spent DESC\nLIMIT 10", "relation_name": "`workspace`.`default`.`top_customers`", "batch_results": null}, {"status": "pass", "timing": [{"name": "compile", "started_at": "2025-08-27T18:25:21.507014Z", "completed_at": "2025-08-27T18:25:21.528821Z"}, {"name": "execute", "started_at": "2025-08-27T18:25:21.530818Z", "completed_at": "2025-08-27T18:25:21.932033Z"}], "thread_id": "Thread-1 (worker)", "execution_time": 0.432201623916626, "adapter_response": {"_message": "OK", "query_id": "01f08373-311a-139e-b04d-8ed113d6a6eb"}, "message": null, "failures": 0, "unique_id": "test.dbt_databricks_cicd.non_negative_avg_discount_by_category_avg_discount_percent.c2755bf97f", "compiled": true, "compiled_code": "\nselect *\nfrom `workspace`.`default`.`avg_discount_by_category`\nwhere TRY_CAST(REPLACE(avg_discount_percent, ',', '.') AS DOUBLE) < 0\n", "relation_name": null, "batch_results": null}, {"status": "pass", "timing": [{"name": "compile", "started_at": "2025-08-27T18:25:21.955995Z", "completed_at": "2025-08-27T18:25:21.989669Z"}, {"name": "execute", "started_at": "2025-08-27T18:25:21.991890Z", "completed_at": "2025-08-27T18:25:22.388789Z"}], "thread_id": "Thread-1 (worker)", "execution_time": 0.4377892017364502, "adapter_response": {"_message": "OK", "query_id": "01f08373-315e-1f56-a210-620e40e7150d"}, "message": null, "failures": 0, "unique_id": "test.dbt_databricks_cicd.not_null_avg_discount_by_category_Category.237c8c010b", "compiled": true, "compiled_code": "\n    \n    \n\n\n\nselect Category\nfrom `workspace`.`default`.`avg_discount_by_category`\nwhere Category is null\n\n\n", "relation_name": null, "batch_results": null}, {"status": "pass", "timing": [{"name": "compile", "started_at": "2025-08-27T18:25:22.401335Z", "completed_at": "2025-08-27T18:25:22.417616Z"}, {"name": "execute", "started_at": "2025-08-27T18:25:22.419398Z", "completed_at": "2025-08-27T18:25:22.803730Z"}], "thread_id": "Thread-1 (worker)", "execution_time": 0.40641093254089355, "adapter_response": {"_message": "OK", "query_id": "01f08373-319e-1a96-b544-f6e2976f7a0a"}, "message": null, "failures": 0, "unique_id": "test.dbt_databricks_cicd.not_null_avg_discount_by_category_avg_discount_percent.622396a101", "compiled": true, "compiled_code": "\n    \n    \n\n\n\nselect avg_discount_percent\nfrom `workspace`.`default`.`avg_discount_by_category`\nwhere avg_discount_percent is null\n\n\n", "relation_name": null, "batch_results": null}, {"status": "pass", "timing": [{"name": "compile", "started_at": "2025-08-27T18:25:22.820225Z", "completed_at": "2025-08-27T18:25:22.836284Z"}, {"name": "execute", "started_at": "2025-08-27T18:25:22.837278Z", "completed_at": "2025-08-27T18:25:23.210417Z"}], "thread_id": "Thread-1 (worker)", "execution_time": 0.39719295501708984, "adapter_response": {"_message": "OK", "query_id": "01f08373-31dd-12ae-ab4b-6bddf7882f1a"}, "message": null, "failures": 0, "unique_id": "test.dbt_databricks_cicd.non_negative_avg_ticket_by_category_avg_ticket.6ca601b095", "compiled": true, "compiled_code": "\nselect *\nfrom `workspace`.`default`.`avg_ticket_by_category`\nwhere TRY_CAST(REPLACE(avg_ticket, ',', '.') AS DOUBLE) < 0\n", "relation_name": null, "batch_results": null}, {"status": "pass", "timing": [{"name": "compile", "started_at": "2025-08-27T18:25:23.221297Z", "completed_at": "2025-08-27T18:25:23.223966Z"}, {"name": "execute", "started_at": "2025-08-27T18:25:23.223966Z", "completed_at": "2025-08-27T18:25:23.635396Z"}], "thread_id": "Thread-1 (worker)", "execution_time": 0.41913628578186035, "adapter_response": {"_message": "OK", "query_id": "01f08373-3219-1bb8-8546-4316a02d4900"}, "message": null, "failures": 0, "unique_id": "test.dbt_databricks_cicd.not_null_avg_ticket_by_category_Category.e0cd76451f", "compiled": true, "compiled_code": "\n    \n    \n\n\n\nselect Category\nfrom `workspace`.`default`.`avg_ticket_by_category`\nwhere Category is null\n\n\n", "relation_name": null, "batch_results": null}, {"status": "pass", "timing": [{"name": "compile", "started_at": "2025-08-27T18:25:23.655739Z", "completed_at": "2025-08-27T18:25:23.680390Z"}, {"name": "execute", "started_at": "2025-08-27T18:25:23.682806Z", "completed_at": "2025-08-27T18:25:24.037768Z"}], "thread_id": "Thread-1 (worker)", "execution_time": 0.3883848190307617, "adapter_response": {"_message": "OK", "query_id": "01f08373-325f-1d4b-a3ed-252ded593c99"}, "message": null, "failures": 0, "unique_id": "test.dbt_databricks_cicd.not_null_avg_ticket_by_category_avg_ticket.68d6992a41", "compiled": true, "compiled_code": "\n    \n    \n\n\n\nselect avg_ticket\nfrom `workspace`.`default`.`avg_ticket_by_category`\nwhere avg_ticket is null\n\n\n", "relation_name": null, "batch_results": null}, {"status": "pass", "timing": [{"name": "compile", "started_at": "2025-08-27T18:25:24.057938Z", "completed_at": "2025-08-27T18:25:24.079937Z"}, {"name": "execute", "started_at": "2025-08-27T18:25:24.081940Z", "completed_at": "2025-08-27T18:25:24.479885Z"}], "thread_id": "Thread-1 (worker)", "execution_time": 0.4299476146697998, "adapter_response": {"_message": "OK", "query_id": "01f08373-329c-190b-9933-62da91180f15"}, "message": null, "failures": 0, "unique_id": "test.dbt_databricks_cicd.non_negative_monthly_revenue_monthly_revenue.68b6895294", "compiled": true, "compiled_code": "\nselect *\nfrom `workspace`.`default`.`monthly_revenue`\nwhere TRY_CAST(REPLACE(monthly_revenue, ',', '.') AS DOUBLE) < 0\n", "relation_name": null, "batch_results": null}, {"status": "pass", "timing": [{"name": "compile", "started_at": "2025-08-27T18:25:24.497586Z", "completed_at": "2025-08-27T18:25:24.514353Z"}, {"name": "execute", "started_at": "2025-08-27T18:25:24.514353Z", "completed_at": "2025-08-27T18:25:24.908254Z"}], "thread_id": "Thread-1 (worker)", "execution_time": 0.416654109954834, "adapter_response": {"_message": "OK", "query_id": "01f08373-32dd-1e89-8ad0-0ab4644b4cb1"}, "message": null, "failures": 0, "unique_id": "test.dbt_databricks_cicd.not_null_monthly_revenue_month.ee51ac609b", "compiled": true, "compiled_code": "\n    \n    \n\n\n\nselect month\nfrom `workspace`.`default`.`monthly_revenue`\nwhere month is null\n\n\n", "relation_name": null, "batch_results": null}, {"status": "pass", "timing": [{"name": "compile", "started_at": "2025-08-27T18:25:24.929333Z", "completed_at": "2025-08-27T18:25:24.946638Z"}, {"name": "execute", "started_at": "2025-08-27T18:25:24.948635Z", "completed_at": "2025-08-27T18:25:25.306266Z"}], "thread_id": "Thread-1 (worker)", "execution_time": 0.3867170810699463, "adapter_response": {"_message": "OK", "query_id": "01f08373-3320-15ac-856d-6592d506c00b"}, "message": null, "failures": 0, "unique_id": "test.dbt_databricks_cicd.not_null_monthly_revenue_monthly_revenue.02fcba701b", "compiled": true, "compiled_code": "\n    \n    \n\n\n\nselect monthly_revenue\nfrom `workspace`.`default`.`monthly_revenue`\nwhere monthly_revenue is null\n\n\n", "relation_name": null, "batch_results": null}, {"status": "pass", "timing": [{"name": "compile", "started_at": "2025-08-27T18:25:25.320774Z", "completed_at": "2025-08-27T18:25:25.343967Z"}, {"name": "execute", "started_at": "2025-08-27T18:25:25.346821Z", "completed_at": "2025-08-27T18:25:25.726351Z"}], "thread_id": "Thread-1 (worker)", "execution_time": 0.4125783443450928, "adapter_response": {"_message": "OK", "query_id": "01f08373-335c-136f-bf56-7f8663980384"}, "message": null, "failures": 0, "unique_id": "test.dbt_databricks_cicd.non_negative_payment_distribution_total_value.c4ae109282", "compiled": true, "compiled_code": "\nselect *\nfrom `workspace`.`default`.`payment_distribution`\nwhere TRY_CAST(REPLACE(total_value, ',', '.') AS DOUBLE) < 0\n", "relation_name": null, "batch_results": null}, {"status": "pass", "timing": [{"name": "compile", "started_at": "2025-08-27T18:25:25.749713Z", "completed_at": "2025-08-27T18:25:25.778455Z"}, {"name": "execute", "started_at": "2025-08-27T18:25:25.780453Z", "completed_at": "2025-08-27T18:25:26.132021Z"}], "thread_id": "Thread-1 (worker)", "execution_time": 0.39164257049560547, "adapter_response": {"_message": "OK", "query_id": "01f08373-339e-169b-afd4-02fe814e99c8"}, "message": null, "failures": 0, "unique_id": "test.dbt_databricks_cicd.not_null_payment_distribution_Payment_Method.bd80df3cae", "compiled": true, "compiled_code": "\n    \n    \n\n\n\nselect Payment_Method\nfrom `workspace`.`default`.`payment_distribution`\nwhere Payment_Method is null\n\n\n", "relation_name": null, "batch_results": null}, {"status": "pass", "timing": [{"name": "compile", "started_at": "2025-08-27T18:25:26.151089Z", "completed_at": "2025-08-27T18:25:26.165496Z"}, {"name": "execute", "started_at": "2025-08-27T18:25:26.166498Z", "completed_at": "2025-08-27T18:25:26.527413Z"}], "thread_id": "Thread-1 (worker)", "execution_time": 0.3804047107696533, "adapter_response": {"_message": "OK", "query_id": "01f08373-33d8-1cfd-b45f-8e94fbe72712"}, "message": null, "failures": 0, "unique_id": "test.dbt_databricks_cicd.not_null_payment_distribution_total_transactions.928411e2e8", "compiled": true, "compiled_code": "\n    \n    \n\n\n\nselect total_transactions\nfrom `workspace`.`default`.`payment_distribution`\nwhere total_transactions is null\n\n\n", "relation_name": null, "batch_results": null}, {"status": "pass", "timing": [{"name": "compile", "started_at": "2025-08-27T18:25:26.557670Z", "completed_at": "2025-08-27T18:25:26.577307Z"}, {"name": "execute", "started_at": "2025-08-27T18:25:26.577307Z", "completed_at": "2025-08-27T18:25:26.943504Z"}], "thread_id": "Thread-1 (worker)", "execution_time": 0.40044713020324707, "adapter_response": {"_message": "OK", "query_id": "01f08373-3419-1362-a824-0773c7e11451"}, "message": null, "failures": 0, "unique_id": "test.dbt_databricks_cicd.not_null_payment_distribution_total_value.58135f5f03", "compiled": true, "compiled_code": "\n    \n    \n\n\n\nselect total_value\nfrom `workspace`.`default`.`payment_distribution`\nwhere total_value is null\n\n\n", "relation_name": null, "batch_results": null}, {"status": "pass", "timing": [{"name": "compile", "started_at": "2025-08-27T18:25:26.963795Z", "completed_at": "2025-08-27T18:25:26.983649Z"}, {"name": "execute", "started_at": "2025-08-27T18:25:26.985643Z", "completed_at": "2025-08-27T18:25:27.378980Z"}], "thread_id": "Thread-1 (worker)", "execution_time": 0.4213733673095703, "adapter_response": {"_message": "OK", "query_id": "01f08373-3459-1731-bbd8-b9c5a1444222"}, "message": null, "failures": 0, "unique_id": "test.dbt_databricks_cicd.non_negative_sales_by_category_total_revenue.8ad171ef41", "compiled": true, "compiled_code": "\nselect *\nfrom `workspace`.`default`.`sales_by_category`\nwhere TRY_CAST(REPLACE(total_revenue, ',', '.') AS DOUBLE) < 0\n", "relation_name": null, "batch_results": null}, {"status": "pass", "timing": [{"name": "compile", "started_at": "2025-08-27T18:25:27.392031Z", "completed_at": "2025-08-27T18:25:27.399057Z"}, {"name": "execute", "started_at": "2025-08-27T18:25:27.406437Z", "completed_at": "2025-08-27T18:25:27.756736Z"}], "thread_id": "Thread-1 (worker)", "execution_time": 0.3697495460510254, "adapter_response": {"_message": "OK", "query_id": "01f08373-3496-1170-abdc-10dba60d0701"}, "message": null, "failures": 0, "unique_id": "test.dbt_databricks_cicd.not_null_sales_by_category_Category.e69cdf4507", "compiled": true, "compiled_code": "\n    \n    \n\n\n\nselect Category\nfrom `workspace`.`default`.`sales_by_category`\nwhere Category is null\n\n\n", "relation_name": null, "batch_results": null}, {"status": "pass", "timing": [{"name": "compile", "started_at": "2025-08-27T18:25:27.767502Z", "completed_at": "2025-08-27T18:25:27.779616Z"}, {"name": "execute", "started_at": "2025-08-27T18:25:27.781609Z", "completed_at": "2025-08-27T18:25:28.163117Z"}], "thread_id": "Thread-1 (worker)", "execution_time": 0.3996131420135498, "adapter_response": {"_message": "OK", "query_id": "01f08373-34ce-1bb0-8f49-ee7dfdb41332"}, "message": null, "failures": 0, "unique_id": "test.dbt_databricks_cicd.not_null_sales_by_category_total_orders.024c423e1e", "compiled": true, "compiled_code": "\n    \n    \n\n\n\nselect total_orders\nfrom `workspace`.`default`.`sales_by_category`\nwhere total_orders is null\n\n\n", "relation_name": null, "batch_results": null}, {"status": "pass", "timing": [{"name": "compile", "started_at": "2025-08-27T18:25:28.175401Z", "completed_at": "2025-08-27T18:25:28.185404Z"}, {"name": "execute", "started_at": "2025-08-27T18:25:28.188403Z", "completed_at": "2025-08-27T18:25:28.531068Z"}], "thread_id": "Thread-1 (worker)", "execution_time": 0.3596656322479248, "adapter_response": {"_message": "OK", "query_id": "01f08373-350c-1971-9e02-a2f8baf1fcb3"}, "message": null, "failures": 0, "unique_id": "test.dbt_databricks_cicd.not_null_sales_by_category_total_revenue.fb1162affd", "compiled": true, "compiled_code": "\n    \n    \n\n\n\nselect total_revenue\nfrom `workspace`.`default`.`sales_by_category`\nwhere total_revenue is null\n\n\n", "relation_name": null, "batch_results": null}, {"status": "pass", "timing": [{"name": "compile", "started_at": "2025-08-27T18:25:28.536146Z", "completed_at": "2025-08-27T18:25:28.557264Z"}, {"name": "execute", "started_at": "2025-08-27T18:25:28.558264Z", "completed_at": "2025-08-27T18:25:28.911528Z"}], "thread_id": "Thread-1 (worker)", "execution_time": 0.3753821849822998, "adapter_response": {"_message": "OK", "query_id": "01f08373-3545-1960-882a-83d8d2991d7e"}, "message": null, "failures": 0, "unique_id": "test.dbt_databricks_cicd.non_negative_top_5_products_total_sales.b51b2dea34", "compiled": true, "compiled_code": "\nselect *\nfrom `workspace`.`default`.`top_5_products`\nwhere TRY_CAST(REPLACE(total_sales, ',', '.') AS DOUBLE) < 0\n", "relation_name": null, "batch_results": null}, {"status": "pass", "timing": [{"name": "compile", "started_at": "2025-08-27T18:25:28.923829Z", "completed_at": "2025-08-27T18:25:28.932791Z"}, {"name": "execute", "started_at": "2025-08-27T18:25:28.934791Z", "completed_at": "2025-08-27T18:25:29.318852Z"}], "thread_id": "Thread-1 (worker)", "execution_time": 0.4001038074493408, "adapter_response": {"_message": "OK", "query_id": "01f08373-357f-1365-9791-3868bb3e5bdd"}, "message": null, "failures": 0, "unique_id": "test.dbt_databricks_cicd.not_null_top_5_products_product_id.c6ac160bfe", "compiled": true, "compiled_code": "\n    \n    \n\n\n\nselect product_id\nfrom `workspace`.`default`.`top_5_products`\nwhere product_id is null\n\n\n", "relation_name": null, "batch_results": null}, {"status": "pass", "timing": [{"name": "compile", "started_at": "2025-08-27T18:25:29.331665Z", "completed_at": "2025-08-27T18:25:29.342644Z"}, {"name": "execute", "started_at": "2025-08-27T18:25:29.344680Z", "completed_at": "2025-08-27T18:25:29.718766Z"}], "thread_id": "Thread-1 (worker)", "execution_time": 0.39336585998535156, "adapter_response": {"_message": "OK", "query_id": "01f08373-35bd-1344-9981-c8b4741c2f57"}, "message": null, "failures": 0, "unique_id": "test.dbt_databricks_cicd.not_null_top_5_products_total_sales.e20b869818", "compiled": true, "compiled_code": "\n    \n    \n\n\n\nselect total_sales\nfrom `workspace`.`default`.`top_5_products`\nwhere total_sales is null\n\n\n", "relation_name": null, "batch_results": null}, {"status": "pass", "timing": [{"name": "compile", "started_at": "2025-08-27T18:25:29.730514Z", "completed_at": "2025-08-27T18:25:29.744509Z"}, {"name": "execute", "started_at": "2025-08-27T18:25:29.746510Z", "completed_at": "2025-08-27T18:25:30.086397Z"}], "thread_id": "Thread-1 (worker)", "execution_time": 0.36063480377197266, "adapter_response": {"_message": "OK", "query_id": "01f08373-35fb-15ef-ad85-a456f5a7503c"}, "message": null, "failures": 0, "unique_id": "test.dbt_databricks_cicd.non_negative_top_customers_total_spent.38e4f29667", "compiled": true, "compiled_code": "\nselect *\nfrom `workspace`.`default`.`top_customers`\nwhere TRY_CAST(REPLACE(total_spent, ',', '.') AS DOUBLE) < 0\n", "relation_name": null, "batch_results": null}, {"status": "pass", "timing": [{"name": "compile", "started_at": "2025-08-27T18:25:30.110976Z", "completed_at": "2025-08-27T18:25:30.121794Z"}, {"name": "execute", "started_at": "2025-08-27T18:25:30.122794Z", "completed_at": "2025-08-27T18:25:30.462964Z"}], "thread_id": "Thread-1 (worker)", "execution_time": 0.3560037612915039, "adapter_response": {"_message": "OK", "query_id": "01f08373-3633-1ed4-8487-5481300fa5f4"}, "message": null, "failures": 0, "unique_id": "test.dbt_databricks_cicd.not_null_top_customers_User_ID.7df96963c0", "compiled": true, "compiled_code": "\n    \n    \n\n\n\nselect User_ID\nfrom `workspace`.`default`.`top_customers`\nwhere User_ID is null\n\n\n", "relation_name": null, "batch_results": null}, {"status": "pass", "timing": [{"name": "compile", "started_at": "2025-08-27T18:25:30.476774Z", "completed_at": "2025-08-27T18:25:30.488767Z"}, {"name": "execute", "started_at": "2025-08-27T18:25:30.490728Z", "completed_at": "2025-08-27T18:25:30.851897Z"}], "thread_id": "Thread-1 (worker)", "execution_time": 0.3801422119140625, "adapter_response": {"_message": "OK", "query_id": "01f08373-366c-11a3-8ba3-3d2a0c742068"}, "message": null, "failures": 0, "unique_id": "test.dbt_databricks_cicd.not_null_top_customers_total_orders.32b439c746", "compiled": true, "compiled_code": "\n    \n    \n\n\n\nselect total_orders\nfrom `workspace`.`default`.`top_customers`\nwhere total_orders is null\n\n\n", "relation_name": null, "batch_results": null}, {"status": "pass", "timing": [{"name": "compile", "started_at": "2025-08-27T18:25:30.867525Z", "completed_at": "2025-08-27T18:25:30.883149Z"}, {"name": "execute", "started_at": "2025-08-27T18:25:30.883149Z", "completed_at": "2025-08-27T18:25:31.219794Z"}], "thread_id": "Thread-1 (worker)", "execution_time": 0.35226893424987793, "adapter_response": {"_message": "OK", "query_id": "01f08373-36a8-190e-b144-85c5acd2def4"}, "message": null, "failures": 0, "unique_id": "test.dbt_databricks_cicd.not_null_top_customers_total_spent.426b0eae73", "compiled": true, "compiled_code": "\n    \n    \n\n\n\nselect total_spent\nfrom `workspace`.`default`.`top_customers`\nwhere total_spent is null\n\n\n", "relation_name": null, "batch_results": null}], "elapsed_time": 19.329301357269287, "args": {"defer": false, "print": true, "show_resource_report": false, "invocation_command": "dbt build --target databricks --select staging+", "select": ["staging+"], "partial_parse": true, "warn_error_options": {"error": [], "warn": [], "silence": []}, "show": false, "show_all_deprecations": false, "quiet": false, "require_yaml_configuration_for_mf_time_spines": false, "log_format_file": "debug", "source_freshness_run_project_hooks": true, "target": "databricks", "cache_selected_only": false, "exclude": [], "include_saved_query": false, "indirect_selection": "eager", "require_batched_execution_for_custom_microbatch_strategy": false, "version_check": true, "require_all_warnings_handled_by_warn_error": false, "project_dir": "D:\\Documentos\\Python-SQL\\Projetos\\Projeto DBT Databricks CICD", "use_colors": true, "vars": {}, "write_json": true, "state_modified_compare_more_unrendered_values": false, "favor_state": false, "send_anonymous_usage_stats": true, "log_format": "default", "skip_nodes_if_on_run_start_fails": false, "export_saved_queries": false, "log_file_max_bytes": 10485760, "state_modified_compare_vars": false, "static_parser": true, "log_level": "info", "empty": false, "require_explicit_package_overrides_for_builtin_materializations": true, "require_nested_cumulative_type_params": false, "log_level_file": "debug", "use_colors_file": true, "resource_types": [], "introspect": true, "exclude_resource_types": [], "which": "build", "printer_width": 80, "profiles_dir": "C:\\Users\\diniz\\.dbt", "require_resource_names_without_spaces": true, "upload_to_artifacts_ingest_api": false, "macro_debugging": false, "partial_parse_file_diff": true, "use_fast_test_edges": false, "strict_mode": false, "log_path": "D:\\Documentos\\Python-SQL\\Projetos\\Projeto DBT Databricks CICD\\logs", "validate_macro_args": false, "populate_cache": true}}